{"Blend,  Just a little bit of milk,  One spoonful of sugar":1,"Blend,  No milk,  No sugar":2,"Blend,  None at all,  None at all":1,"Blend,  The regular amount of milk,   Two spoonfuls of sugar":1,"Blend, A little bit of milk,  One sugar":1,"Blend, Just a little bit of milk,  One spoonful of sugar":1,"Blend, Just a little bit of milk,One spoonful of sugar":1,"Blend, Lots of milk,  Three spoonfuls of sugar":1,"Blend, Lots of milk, 3 spoonfuls of sugar":1,"Blend, Lots of milk, Three spoonfuls of sugar":2,"Blend, Lots of milk,Three spoonfuls of sugar":1,"Blend, No milk, No sugar":1,"Blend, No milk, No sugar.":1,"Blend, None at all, None at all":3,"Blend, The regular amount of milk,  Two spoonfuls of sugar":1,"Blend, The regular amount of milk, Two spoonfuls of sugar":2,"Blend, The regular amount of milk,Two spoonfuls of sugar":1,"Blend,A little bit of milk,1 spoonful of sugar":3,"Blend,A little bit of milk,One spoonful of sugar":5,"Blend,Just a little bit of milk,One spoonful of sugar":9,"Blend,Lots of milk,3 spoonfuls of sugar":2,"Blend,Lots of milk,Three spoonfuls of sugar":12,"Blend,No milk,No sugar":8,"Blend,None at all,None at all":12,"Blend,The regular amount of milk,2 spoonfuls of sugar":2,"Blend,The regular amount of milk,Two spoonfuls of sugar":9,"Blue Mountain,  A little bit of milk, One spoonful of sugar":1,"Blue Mountain,  None at all,  None at all":1,"Blue Mountain,  The regular amount of milk,  Two spoonfuls of sugar":2,"Blue Mountain, A little bit of milk,One spoonful of sugar":1,"Blue Mountain, Just a little bit of milk,  1 spoonful of sugar":1,"Blue Mountain, Lots of milk,  Three spoonfuls of sugar":1,"Blue Mountain, Lots of milk, 3 spoonfuls of sugar":1,"Blue Mountain, Lots of milk, Three spoonfuls of sugar":2,"Blue Mountain, Lots of milk, Three spoonfuls of sugar.":1,"Blue Mountain, Lots of milk,Three spoonfuls of sugar":1,"Blue Mountain, No milk, No sugar":1,"Blue Mountain, The regular amount of milk, Two spoonfuls of sugar":1,"Blue Mountain, The regular amount of milk,Two spoonfuls of sugar":3,"Blue Mountain,A little bit of milk,One spoonful of sugar":7,"Blue Mountain,Just a  little bit of milk,One spoonful of sugar":1,"Blue Mountain,Just a little bit of milk, One spoonful of sugar":1,"Blue Mountain,Just a little bit of milk,One spoonful of sugar":4,"Blue Mountain,Lots of milk,3 spoonfuls of sugar":3,"Blue Mountain,Lots of milk,Three spoonfuls of sugar":19,"Blue Mountain,No Milk,No Sugar":1,"Blue Mountain,No milk,No sugar":6,"Blue Mountain,None at all,None at all":8,"Blue Mountain,Regular amount of milk,Two spoonfuls of sugar":2,"Blue Mountain,The regular amount of milk,2 spoonfuls of sugar":1,"Blue Mountain,The regular amount of milk,Two spoonfuls of sugar":15,"Blue mountain, lots of milk, 3 spoonfuls of sugar":1,"Blue mountain,Lots of milk,3 spoonfuls of sugar":1,"Blue mountain,The regular amount of milk,Two spoonfuls of sugar":1,"House blend,The regular amount of milk,Two spoonfuls of sugar":1,"Kilamanjaro,A little bit of milk,One spoonful of sugar":1,"Kilamanjaro,Lots of milk,Three spoonfuls of sugar":3,"Kilamanjaro,No milk,No sugar":1,"Kilamanjaro,None at all,None at all":1,"Kilimanjaro,  A little bit of milk, One spoonful of sugar":1,"Kilimanjaro,  A lot of milk,  Three spoonfuls of sugar":1,"Kilimanjaro,  Just a little bit of milk,  One spoonful of sugar":1,"Kilimanjaro, A little bit of milk, 1 spoonful of sugar":1,"Kilimanjaro, A little bit of milk, One spoonful of sugar":1,"Kilimanjaro, A little bit of milk,1 spoonful of sugar":1,"Kilimanjaro, Just a little bit of milk,One spoonful of sugar":2,"Kilimanjaro, Lots of milk, 3 spoonfuls of sugar":1,"Kilimanjaro, Lots of milk, Three spoonfuls of sugar":1,"Kilimanjaro, None at all, None at all":3,"Kilimanjaro, The regular amount of milk,  Two spoonfuls of sugar":1,"Kilimanjaro, The regular amount of milk, 2 spoonfuls of sugar":1,"Kilimanjaro, The regular amount of milk, Two spoonfuls of sugar":1,"Kilimanjaro, a little bit of milk, 1 spoonful of sugar":1,"Kilimanjaro,A little bit of milk, One spoonful of sugar":1,"Kilimanjaro,A little bit of milk,One spoonful of sugar":7,"Kilimanjaro,A lot of milk,Three spoonfuls of sugar":1,"Kilimanjaro,Just a little bit of milk, One spoonful of sugar":1,"Kilimanjaro,Just a little bit of milk,One spoonful of sugar":15,"Kilimanjaro,Lots of milk,3 spoonfuls of sugar":2,"Kilimanjaro,Lots of milk,Three spoonfuls of sugar":11,"Kilimanjaro,No milk,No sugar":10,"Kilimanjaro,None at all,None at all":10,"Kilimanjaro,The regular amount of milk,2 spoonfuls of sugar":1,"Kilimanjaro,The regular amount of milk,Two spoonfuls of sugar":10,"Kilimanjaro,a little bit of milk,one spoonful of sugar":1,"Killimanjaro, None at all, None at all":1,"Mocha,  Lots of milk,  Three spoonfuls of sugar":1,"Mocha,  No milk,  No sugar":4,"Mocha,  The regular amount of milk,  Two spoonfuls of sugar":1,"Mocha,  The regular amount of milk,  Two sugars":1,"Mocha, A little bit of milk,One spoonful of sugar":2,"Mocha, Just a little bit of milk,  One spoonful of sugar":1,"Mocha, Just a little bit of milk, One spoonful of sugar":2,"Mocha, Lots of milk,  Three spoonfuls of sugar":1,"Mocha, Lots of milk, Three spoonfuls of sugar":2,"Mocha, Lots of milk,Three spoonfuls of sugar":1,"Mocha, No milk, No sugar":2,"Mocha, None at all, None at all":1,"Mocha, The regular amount of milk, Two spoonfuls of sugar":1,"Mocha, The regular amount of milk,Two spoonfuls of sugar":1,"Mocha, a little bit of milk, 1 spoonful of sugar":2,"Mocha, none at all, none at all":1,"Mocha,A little bit of milk,1 spoonful of sugar":5,"Mocha,A little bit of milk,One spoonful of sugar":5,"Mocha,Just a little bit of milk,One spoonful of sugar":12,"Mocha,Lots of milk,3 spoonfuls of sugar":2,"Mocha,Lots of milk,Three spoonfuls of sugar":14,"Mocha,No milk, No sugar":1,"Mocha,No milk,No sugar":19,"Mocha,None at all,None at all":7,"Mocha,The regular amount of milk, 2 spoonfuls of sugar":1,"Mocha,The regular amount of milk, Two spoonfuls of sugar":2,"Mocha,The regular amount of milk,2 spoonfuls of sugar":4,"Mocha,The regular amount of milk,Two spoonfuls of sugar":19,"Mocha,The regular amount of milk,Two spoonfuls sugar":1,"None":1,"Unknown":6}